escape_captivity/__about__.py
escape_captivity/__init__.py
escape_captivity/__main__.py
escape_captivity/detect_captive_portal.py
escape_captivity/dispatcher.py
escape_captivity/cli/__init__.py
escape_captivity/solver/__init__.py
escape_captivity/solver/abellio.py
escape_captivity/solver/base.py
escape_captivity/solver/db_regio_southeast.py
escape_captivity/solver/db_station.py
escape_captivity/solver/enno.py
escape_captivity/solver/ice.py
escape_captivity-1.2.0.dist-info/METADATA
escape_captivity-1.2.0.dist-info/WHEEL
escape_captivity-1.2.0.dist-info/entry_points.txt
escape_captivity-1.2.0.dist-info/licenses/LICENSE.txt
escape_captivity-1.2.0.dist-info/RECORD
